felesviz/__init__.py
felesviz/main.py
felesviz/pruebita.py
felesviz-0.2.5.dist-info/LICENSE
felesviz-0.2.5.dist-info/METADATA
felesviz-0.2.5.dist-info/WHEEL
felesviz-0.2.5.dist-info/top_level.txt
felesviz-0.2.5.dist-info/RECORD
