Metadata-Version: 2.1
Name: felesviz
Version: 0.2.5
Summary: Acciones para facilitar la vida de un científico de datos
Author: Miguel Feles
License: MIT License
Keywords: Annotation
Classifier: Development Status :: 3 - Alpha
Classifier: Operating System :: OS Independent
Classifier: License :: OSI Approved :: MIT License
Classifier: Programming Language :: Python :: 3
Requires-Python: >=3.5
License-File: LICENSE
Requires-Dist: opencv-python
Requires-Dist: natsort
